sourav0407/__init__.py
sourav0407/main.py
souravroy0407/__init__.py
souravroy0407/birthday.py
souravroy0407/main.py
souravroy0407-0.6.dist-info/METADATA
souravroy0407-0.6.dist-info/WHEEL
souravroy0407-0.6.dist-info/entry_points.txt
souravroy0407-0.6.dist-info/top_level.txt
souravroy0407-0.6.dist-info/RECORD
