Metadata-Version: 2.1
Name: souravroy0407
Version: 0.6
Summary: A simple package with a hello function
Author: souravroy0407
Classifier: Programming Language :: Python :: 3
Classifier: License :: OSI Approved :: MIT License
Classifier: Operating System :: OS Independent
